saltext/ldap/__init__.py
saltext/ldap/build.py
saltext/ldap/libldap/bin/ldapadd
saltext/ldap/libldap/bin/ldapcompare
saltext/ldap/libldap/bin/ldapdelete
saltext/ldap/libldap/bin/ldapexop
saltext/ldap/libldap/bin/ldapmodify
saltext/ldap/libldap/bin/ldapmodrdn
saltext/ldap/libldap/bin/ldappasswd
saltext/ldap/libldap/bin/ldapsearch
saltext/ldap/libldap/bin/ldapurl
saltext/ldap/libldap/bin/ldapvc
saltext/ldap/libldap/bin/ldapwhoami
saltext/ldap/libldap/etc/openldap/ldap.conf
saltext/ldap/libldap/etc/openldap/ldap.conf.default
saltext/ldap/libldap/etc/openldap/slapd.conf
saltext/ldap/libldap/etc/openldap/slapd.conf.default
saltext/ldap/libldap/etc/openldap/slapd.ldif
saltext/ldap/libldap/etc/openldap/slapd.ldif.default
saltext/ldap/libldap/etc/openldap/schema/README
saltext/ldap/libldap/etc/openldap/schema/collective.ldif
saltext/ldap/libldap/etc/openldap/schema/collective.schema
saltext/ldap/libldap/etc/openldap/schema/corba.ldif
saltext/ldap/libldap/etc/openldap/schema/corba.schema
saltext/ldap/libldap/etc/openldap/schema/core.ldif
saltext/ldap/libldap/etc/openldap/schema/core.schema
saltext/ldap/libldap/etc/openldap/schema/cosine.ldif
saltext/ldap/libldap/etc/openldap/schema/cosine.schema
saltext/ldap/libldap/etc/openldap/schema/dsee.ldif
saltext/ldap/libldap/etc/openldap/schema/dsee.schema
saltext/ldap/libldap/etc/openldap/schema/duaconf.ldif
saltext/ldap/libldap/etc/openldap/schema/duaconf.schema
saltext/ldap/libldap/etc/openldap/schema/dyngroup.ldif
saltext/ldap/libldap/etc/openldap/schema/dyngroup.schema
saltext/ldap/libldap/etc/openldap/schema/inetorgperson.ldif
saltext/ldap/libldap/etc/openldap/schema/inetorgperson.schema
saltext/ldap/libldap/etc/openldap/schema/java.ldif
saltext/ldap/libldap/etc/openldap/schema/java.schema
saltext/ldap/libldap/etc/openldap/schema/misc.ldif
saltext/ldap/libldap/etc/openldap/schema/misc.schema
saltext/ldap/libldap/etc/openldap/schema/msuser.ldif
saltext/ldap/libldap/etc/openldap/schema/msuser.schema
saltext.ldap-0.0.3.dist-info/LICENSE.md
saltext.ldap-0.0.3.dist-info/METADATA
saltext.ldap-0.0.3.dist-info/WHEEL
saltext.ldap-0.0.3.dist-info/entry_points.txt
saltext.ldap-0.0.3.dist-info/top_level.txt
saltext.ldap-0.0.3.dist-info/RECORD
